Metadata-Version: 2.4
Name: tech-aurora-mcp-demo
Version: 0.1.0
Summary: Add your description here
Author-email: 嘉宇 刘 <487954186@qq.com>
Requires-Python: >=3.13.2
Requires-Dist: mcp[cli]>=1.10.1
